cloud_insight-0.0.3.dist-info/METADATA
cloud_insight-0.0.3.dist-info/RECORD
cloud_insight-0.0.3.dist-info/WHEEL
cloud_insight-0.0.3.dist-info/entry_points.txt
cloud_insight-0.0.3.dist-info/top_level.txt
packages/__init__.py
packages/asg.py
packages/aws.py
packages/cli.py
packages/containers.py
packages/docker_api.py
packages/ec2.py
packages/ecr.py
packages/ecs.py
packages/elb.py
packages/executor.py
packages/hashicorp.py
packages/output.py
packages/settings.py
