Metadata-Version: 2.1
Name: cloud-insight
Version: 0.0.3
Summary: Simplifies the tracking of docker container versions, health and other important information across various platforms.
Home-page: https://github.com/noahjohnhay/cloud-insight
Author: Noah Hay
Author-email: noahjohnhay@gmail.com
License: MIT
Platform: UNKNOWN
Classifier: License :: OSI Approved :: MIT License
Classifier: Programming Language :: Python
Classifier: Programming Language :: Python :: 2.6
Classifier: Programming Language :: Python :: 2.7
Classifier: Programming Language :: Python :: Implementation :: CPython
Classifier: Programming Language :: Python :: Implementation :: PyPy
Requires-Dist: boto3
Requires-Dist: cement
Requires-Dist: plotly
Requires-Dist: PrettyTable
Requires-Dist: python-consul
